linear/CDLL.py
linear/CSLL.py
linear/DLL.py
linear/LLQueue.py
linear/LLStack.py
linear/SLL.py
linear/__init__.py
nodes/DNode.py
nodes/SNode.py
nodes/Tnode.py
nodes/__init__.py
trees/AVL.py
trees/BST.py
trees/__init__.py
python_library_30140721-1.8.0.dist-info/METADATA
python_library_30140721-1.8.0.dist-info/WHEEL
python_library_30140721-1.8.0.dist-info/top_level.txt
python_library_30140721-1.8.0.dist-info/RECORD
